MANIFEST.in
README.txt
setup.py
collective/__init__.py
collective.portlet.foldercontents.egg-info/PKG-INFO
collective.portlet.foldercontents.egg-info/SOURCES.txt
collective.portlet.foldercontents.egg-info/dependency_links.txt
collective.portlet.foldercontents.egg-info/entry_points.txt
collective.portlet.foldercontents.egg-info/namespace_packages.txt
collective.portlet.foldercontents.egg-info/not-zip-safe
collective.portlet.foldercontents.egg-info/requires.txt
collective.portlet.foldercontents.egg-info/top_level.txt
collective/portlet/__init__.py
collective/portlet/foldercontents/__init__.py
collective/portlet/foldercontents/configure.zcml
collective/portlet/foldercontents/foldercontents.pt
collective/portlet/foldercontents/foldercontents.py
collective/portlet/foldercontents/scales.py
collective/portlet/foldercontents/widget.py
collective/portlet/foldercontents/locales/collective.portlet.foldercontents.pot
collective/portlet/foldercontents/locales/uk/LC_MESSAGES/collective.portlet.foldercontents.po
collective/portlet/foldercontents/profiles/default/metadata.xml
collective/portlet/foldercontents/profiles/default/portlets.xml
collective/portlet/foldercontents/tests/__init__.py
collective/portlet/foldercontents/tests/base.py
collective/portlet/foldercontents/tests/test_foldercontentsportlet.py
docs/HISTORY.txt
docs/INSTALL.txt
docs/LICENSE.GPL
docs/LICENSE.txt