Metadata-Version: 1.0
Name: collective.portlet.foldercontents
Version: 1.0
Summary: This package provides portlet to list your Plone folder's contents.
Home-page: https://svn.plone.org/svn/collective/collective.portlet.foldercontents/trunk
Author: Vitaliy Podoba
Author-email: vitaliy@martinschoel.com
License: GPL
Keywords: portlet folder contents
Platform: UNKNOWN
Classifier: Framework :: Plone
Classifier: Programming Language :: Python
